vllm_judge/__init__.py
vllm_judge/batch.py
vllm_judge/builtin_metrics.py
vllm_judge/cli.py
vllm_judge/client.py
vllm_judge/exceptions.py
vllm_judge/judge.py
vllm_judge/models.py
vllm_judge/parsers.py
vllm_judge/prompt_builder.py
vllm_judge/templating.py
vllm_judge/api/__init__.py
vllm_judge/api/client.py
vllm_judge/api/models.py
vllm_judge/api/server.py
vllm_judge-0.1.8.dist-info/licenses/LICENSE
vllm_judge-0.1.8.dist-info/METADATA
vllm_judge-0.1.8.dist-info/WHEEL
vllm_judge-0.1.8.dist-info/entry_points.txt
vllm_judge-0.1.8.dist-info/top_level.txt
vllm_judge-0.1.8.dist-info/RECORD
