Metadata-Version: 2.4
Name: vllm_judge
Version: 0.1.8
Summary: LLM-as-a-Judge evaluations for vLLM hosted models
Author: TrustyAI team
Author-email: Sai Chandra Pandraju <saichandrapandraju@gmail.com>
Project-URL: Homepage, https://trustyai.org/vllm_judge/
Project-URL: Repository, https://github.com/trustyai-explainability/vllm_judge
Project-URL: Issues, https://github.com/trustyai-explainability/vllm_judge/issues
Keywords: llm,evaluation,vllm,judge,ai,machine-learning,nlp,llm-evaluation,llm-as-judge
Requires-Python: >=3.8
License-File: LICENSE
Requires-Dist: httpx>=0.24.0
Requires-Dist: pydantic>=2.0.0
Requires-Dist: tenacity>=8.0.0
Requires-Dist: click>=8.0.0
Requires-Dist: numpy>=2.0.0
Provides-Extra: api
Requires-Dist: fastapi>=0.100.0; extra == "api"
Requires-Dist: uvicorn[standard]>=0.22.0; extra == "api"
Requires-Dist: websockets>=11.0; extra == "api"
Provides-Extra: jinja2
Requires-Dist: jinja2>=3.0.0; extra == "jinja2"
Provides-Extra: test
Requires-Dist: pytest>=7.0.0; extra == "test"
Requires-Dist: pytest-asyncio>=0.21.0; extra == "test"
Requires-Dist: pytest-cov>=4.0.0; extra == "test"
Requires-Dist: pytest-mock>=3.10.0; extra == "test"
Provides-Extra: docs
Requires-Dist: mkdocs>=1.5.0; extra == "docs"
Requires-Dist: mkdocs-material>=9.0.0; extra == "docs"
Requires-Dist: mkdocstrings[python]>=0.24.0; extra == "docs"
Requires-Dist: mkdocs-material-extensions>=1.3.1; extra == "docs"
Provides-Extra: dev
Requires-Dist: vllm_judge[api,docs,jinja2,test]; extra == "dev"
Requires-Dist: black>=23.0.0; extra == "dev"
Requires-Dist: isort>=5.12.0; extra == "dev"
Requires-Dist: flake8>=6.0.0; extra == "dev"
Requires-Dist: mypy>=1.0.0; extra == "dev"
Dynamic: license-file
